{
  "schema_version": "8.0-pdf-layout-rebuilt",
  "id": "bari-sulfat",
  "title": "Bari Sulfat",
  "aliases": [
    "bari sulfat",
    "bari sulfate"
  ],
  "source": {
    "book": "Dược thư Quốc gia Việt Nam",
    "edition": "Lần xuất bản thứ ba, 2023",
    "pdf_pages": {
      "start": 264,
      "end": 265
    },
    "printed_pages": {
      "start": 270,
      "end": 271
    },
    "extraction": {
      "start_title_pdf_page": 264,
      "start_column": "right",
      "start_y": 218.1,
      "next_title_pdf_page": 265,
      "next_column": "right",
      "next_y": 62.83
    }
  },
  "sections": [
    {
      "id": "thong-tin-dau-chuyen-luan",
      "title": "Thông tin đầu chuyên luận",
      "content": "BARI SULFAT",
      "blocks": [
        {
          "type": "text",
          "text": "BARI SULFAT"
        }
      ],
      "subsections": []
    },
    {
      "id": "ten-chung-quoc-te",
      "title": "Tên chung quốc tế",
      "content": "Barium sulfate.",
      "blocks": [
        {
          "type": "text",
          "text": "Barium sulfate."
        }
      ],
      "subsections": []
    },
    {
      "id": "ma-atc",
      "title": "Mã ATC",
      "content": "V08BA01, V08BA02.",
      "blocks": [
        {
          "type": "text",
          "text": "V08BA01, V08BA02."
        }
      ],
      "subsections": []
    },
    {
      "id": "loai-thuoc",
      "title": "Loại thuốc",
      "content": "Thuốc cản quang (không phối hợp) đường tiêu hóa.",
      "blocks": [
        {
          "type": "text",
          "text": "Thuốc cản quang (không phối hợp) đường tiêu hóa."
        }
      ],
      "subsections": []
    },
    {
      "id": "dang-thuoc-va-ham-luong",
      "title": "Dạng thuốc và hàm lượng",
      "content": "Hỗn dịch uống: 96,25% (bình 300 ml), 100% (bình 300 ml). Bột nhão uống: Tuýp 150 g (70 g bari sulfat/100 g). Túi thụt trực tràng: 70% (400 ml) (cung cấp trong bộ thụt trực tràng). Bột pha hỗn dịch: 140 g, 200 g. Viên nén: 650 mg.",
      "blocks": [
        {
          "type": "text",
          "text": "Hỗn dịch uống: 96,25% (bình 300 ml), 100% (bình 300 ml). Bột nhão uống: Tuýp 150 g (70 g bari sulfat/100 g). Túi thụt trực tràng: 70% (400 ml) (cung cấp trong bộ thụt trực tràng). Bột pha hỗn dịch: 140 g, 200 g. Viên nén: 650 mg."
        }
      ],
      "subsections": []
    },
    {
      "id": "duoc-luc-hoc",
      "title": "Dược lực học",
      "content": "Bari sulfat là một muối kim loại không hòa tan trong nước và trong các dung môi hữu cơ, rất ít tan trong acid và hydroxyd kiềm. Bari sulfat thường được dùng dưới dạng hỗn dịch uống hoặc thụt hậu môn, hoặc dưới dạng bột nhão uống để làm chất cản quang trong xét nghiệm X-quang đường tiêu hóa. Bari là một kim loại có khối lượng nguyên tử 137, có tính chất hấp thụ mạnh tia X. Hỗn dịch hoặc bột nhão bari sulfat tùy theo nồng độ được dùng theo đường uống hay đường trực tràng để bao phủ lên ống tiêu hóa làm rõ tổn thương trên phim X-quang, dùng trong kỹ thuật tương phản đơn hoặc kép hoặc chụp cắt lớp điện toán. Hỗn dịch bari sulfat ổn định, đồng nhất, có tỷ trọng 1,8 g/cm3 với nồng độ 1 g bari sulfat trong 1 ml và có độ nhớt 2 000 cP, ở nhiệt độ 25 °C. Vì bari sulfat không hòa tan trong nước nên không có độc tính nặng như ion bari. Tử vong đã xảy ra khi dùng nhầm bari sulfid là một chất hòa tan trong nước.",
      "blocks": [
        {
          "type": "text",
          "text": "Bari sulfat là một muối kim loại không hòa tan trong nước và trong các dung môi hữu cơ, rất ít tan trong acid và hydroxyd kiềm. Bari sulfat thường được dùng dưới dạng hỗn dịch uống hoặc thụt hậu môn, hoặc dưới dạng bột nhão uống để làm chất cản quang trong xét nghiệm X-quang đường tiêu hóa. Bari là một kim loại có khối lượng nguyên tử 137, có tính chất hấp thụ mạnh tia X. Hỗn dịch hoặc bột nhão bari sulfat tùy theo nồng độ được dùng theo đường uống hay đường trực tràng để bao phủ lên ống tiêu hóa làm rõ tổn thương trên phim X-quang, dùng trong kỹ thuật tương phản đơn hoặc kép hoặc chụp cắt lớp điện toán. Hỗn dịch bari sulfat ổn định, đồng nhất, có tỷ trọng 1,8 g/cm3 với nồng độ 1 g bari sulfat trong 1 ml và có độ nhớt 2 000 cP, ở nhiệt độ 25 °C. Vì bari sulfat không hòa tan trong nước nên không có độc tính nặng như ion bari. Tử vong đã xảy ra khi dùng nhầm bari sulfid là một chất hòa tan trong nước."
        }
      ],
      "subsections": []
    },
    {
      "id": "duoc-dong-hoc",
      "title": "Dược động học",
      "content": "Do tính chất không hòa tan trong nước và trong các dung môi hữu cơ nên bari sulfat không hấp thu qua đường tiêu hóa.",
      "blocks": [
        {
          "type": "text",
          "text": "Do tính chất không hòa tan trong nước và trong các dung môi hữu cơ nên bari sulfat không hấp thu qua đường tiêu hóa."
        }
      ],
      "subsections": []
    },
    {
      "id": "chi-dinh",
      "title": "Chỉ định",
      "content": "Thuốc cản quang dùng để thăm khám bằng X-quang toàn bộ đường tiêu hóa và theo dõi thời gian vận chuyển qua đường tiêu hóa.",
      "blocks": [
        {
          "type": "text",
          "text": "Thuốc cản quang dùng để thăm khám bằng X-quang toàn bộ đường tiêu hóa và theo dõi thời gian vận chuyển qua đường tiêu hóa."
        }
      ],
      "subsections": []
    },
    {
      "id": "chong-chi-dinh",
      "title": "Chống chỉ định",
      "content": "Tắc nghẽn hoặc thủng trên đường tiêu hóa.",
      "blocks": [
        {
          "type": "text",
          "text": "Tắc nghẽn hoặc thủng trên đường tiêu hóa."
        }
      ],
      "subsections": []
    },
    {
      "id": "than-trong",
      "title": "Thận trọng",
      "content": "Bari sulfat không được chỉ định cho người bệnh bị tắc ruột và phải thận trọng đối với người có chứng hẹp môn vị hoặc có tổn thương dễ dẫn đến tắc nghẽn ống tiêu hóa. Phải tránh dùng thuốc, nhất là cho qua đường hậu môn, ở những người có nguy cơ bị thủng như trong viêm đại tràng loét cấp hoặc viêm túi thừa Meckel, sau khi làm sinh thiết trực tràng hoặc đại tràng, soi đại tràng sigma hoặc quang tuyến liệu pháp. Thận trọng đối với người bị suy kiệt nặng. Để tránh táo bón sau khi dùng bari sulfat, cần cho người bệnh uống nước đủ.\n\nVì bari sulfat có tính chất trơ nên những vết mờ còn để lại sẽ cản trở cho những lần chụp X-quang tiếp theo.",
      "blocks": [
        {
          "type": "text",
          "text": "Bari sulfat không được chỉ định cho người bệnh bị tắc ruột và phải thận trọng đối với người có chứng hẹp môn vị hoặc có tổn thương dễ dẫn đến tắc nghẽn ống tiêu hóa. Phải tránh dùng thuốc, nhất là cho qua đường hậu môn, ở những người có nguy cơ bị thủng như trong viêm đại tràng loét cấp hoặc viêm túi thừa Meckel, sau khi làm sinh thiết trực tràng hoặc đại tràng, soi đại tràng sigma hoặc quang tuyến liệu pháp. Thận trọng đối với người bị suy kiệt nặng. Để tránh táo bón sau khi dùng bari sulfat, cần cho người bệnh uống nước đủ."
        },
        {
          "type": "text",
          "text": "Vì bari sulfat có tính chất trơ nên những vết mờ còn để lại sẽ cản trở cho những lần chụp X-quang tiếp theo."
        }
      ],
      "subsections": []
    },
    {
      "id": "thoi-ky-mang-thai",
      "title": "Thời kỳ mang thai",
      "content": "Chưa có tài liệu nghiên cứu cho thấy tai biến khi dùng bari sulfat cho người mang thai. Nói chung, nên tránh tất cả các loại thăm dò bằng X-quang ở người mang thai.",
      "blocks": [
        {
          "type": "text",
          "text": "Chưa có tài liệu nghiên cứu cho thấy tai biến khi dùng bari sulfat cho người mang thai. Nói chung, nên tránh tất cả các loại thăm dò bằng X-quang ở người mang thai."
        }
      ],
      "subsections": []
    },
    {
      "id": "thoi-ky-cho-con-bu",
      "title": "Thời kỳ cho con bú",
      "content": "Chưa có tài liệu nghiên cứu cho thấy tai biến khi dùng bari sulfat cho người cho con bú. Nói chung, cần thận trọng khi dùng thuốc cho người mẹ đang cho con bú.",
      "blocks": [
        {
          "type": "text",
          "text": "Chưa có tài liệu nghiên cứu cho thấy tai biến khi dùng bari sulfat cho người cho con bú. Nói chung, cần thận trọng khi dùng thuốc cho người mẹ đang cho con bú."
        }
      ],
      "subsections": []
    },
    {
      "id": "tac-dung-khong-mong-muon",
      "title": "Tác dụng không mong muốn",
      "content": "(ADR) Thường gặp và rất thường gặp Tiêu hóa: Táo bón (có thể ngăn ngừa táo bón bằng cách cho người bệnh dùng thuốc nhuận tràng nhẹ sau khi kiểm tra X-quang). Hiếm gặp và rất hiếm gặp Toàn thân: dị ứng phản vệ (khi dùng hỗn dịch bari sulfat). Da: nổi mày đay, phù mặt.",
      "blocks": [
        {
          "type": "text",
          "text": "(ADR) Thường gặp và rất thường gặp Tiêu hóa: Táo bón (có thể ngăn ngừa táo bón bằng cách cho người bệnh dùng thuốc nhuận tràng nhẹ sau khi kiểm tra X-quang). Hiếm gặp và rất hiếm gặp Toàn thân: dị ứng phản vệ (khi dùng hỗn dịch bari sulfat). Da: nổi mày đay, phù mặt."
        }
      ],
      "subsections": []
    },
    {
      "id": "lieu-luong-va-cach-dung",
      "title": "Liều lượng và cách dùng",
      "content": "Liều lượng bari sulfat phụ thuộc vào loại thăm khám và kỹ thuật dùng. Thực quản: Uống ≤ 150 ml hỗn dịch nồng độ 50 - 200% (khối lượng/thể tích). Dạ dày và tá tràng: Uống ≤ 300 ml hỗn dịch nồng độ 30 - 200%. Tiểu tràng: Uống 100 - 300 ml hỗn dịch nồng độ 30 - 150%. Đại tràng: Thụt 200 ml tới 2 lít hỗn dịch có nồng độ 20 - 130%. Phần trên ống tiêu hóa (hầu, hạ hầu, thực quản): Uống bột nhão 2 - 4 thìa canh tùy theo vị trí thăm khám. Để có các hình ảnh tốt nhất (không có bọt không khí), phải nuốt không nhai. Thăm khám X-quang phải thực hiện lúc đói đối với ống tiêu hóa phần trên. Đối với đường tiêu hóa dưới, phải thụt tháo buổi tối và ăn chế độ ít cặn bã 3 ngày trước khi xét nghiệm. Hỗn dịch có nồng độ 1,6 - 2,2% có thể dùng để chụp cắt lớp điện toán đường tiêu hóa. Để thực hiện tương phản kép, có thể đưa khí vào đường tiêu hóa bằng cách dùng các hỗn dịch bari sulfat chứa carbon dioxyd. Cũng có các chế phẩm có natri bicarbonat để tạo khí riêng. Không khí có thể đưa vào qua một ống để thay thế carbon dioxyd. Thuốc cản quang và siêu âm đều đã được dùng để chẩn đoán lồng ruột, nhưng siêu âm thường được đánh giá cao hơn trong chẩn đoán, còn thụt để dành cho tháo lồng ruột. Hỗn dịch bari sulfat đã được dùng từ nhiều năm để chẩn đoán lồng ruột và tháo lồng, nhưng hiện nay nhiều nơi đã thay thế hỗn dịch bari sulfat bằng thụt tháo lồng bằng không khí hoặc bằng thụt nước muối có siêu âm hướng dẫn để giảm nguy cơ viêm màng bụng do chất hóa học nếu xảy ra thủng ruột.",
      "blocks": [
        {
          "type": "text",
          "text": "Liều lượng bari sulfat phụ thuộc vào loại thăm khám và kỹ thuật dùng. Thực quản: Uống ≤ 150 ml hỗn dịch nồng độ 50 - 200% (khối lượng/thể tích). Dạ dày và tá tràng: Uống ≤ 300 ml hỗn dịch nồng độ 30 - 200%. Tiểu tràng: Uống 100 - 300 ml hỗn dịch nồng độ 30 - 150%. Đại tràng: Thụt 200 ml tới 2 lít hỗn dịch có nồng độ 20 - 130%. Phần trên ống tiêu hóa (hầu, hạ hầu, thực quản): Uống bột nhão 2 - 4 thìa canh tùy theo vị trí thăm khám. Để có các hình ảnh tốt nhất (không có bọt không khí), phải nuốt không nhai. Thăm khám X-quang phải thực hiện lúc đói đối với ống tiêu hóa phần trên. Đối với đường tiêu hóa dưới, phải thụt tháo buổi tối và ăn chế độ ít cặn bã 3 ngày trước khi xét nghiệm. Hỗn dịch có nồng độ 1,6 - 2,2% có thể dùng để chụp cắt lớp điện toán đường tiêu hóa. Để thực hiện tương phản kép, có thể đưa khí vào đường tiêu hóa bằng cách dùng các hỗn dịch bari sulfat chứa carbon dioxyd. Cũng có các chế phẩm có natri bicarbonat để tạo khí riêng. Không khí có thể đưa vào qua một ống để thay thế carbon dioxyd. Thuốc cản quang và siêu âm đều đã được dùng để chẩn đoán lồng ruột, nhưng siêu âm thường được đánh giá cao hơn trong chẩn đoán, còn thụt để dành cho tháo lồng ruột. Hỗn dịch bari sulfat đã được dùng từ nhiều năm để chẩn đoán lồng ruột và tháo lồng, nhưng hiện nay nhiều nơi đã thay thế hỗn dịch bari sulfat bằng thụt tháo lồng bằng không khí hoặc bằng thụt nước muối có siêu âm hướng dẫn để giảm nguy cơ viêm màng bụng do chất hóa học nếu xảy ra thủng ruột."
        }
      ],
      "subsections": []
    },
    {
      "id": "qua-lieu-va-xu-tri",
      "title": "Quá liều và xử trí",
      "content": "Khi chỉ định nhầm hoặc do quá trình chụp gây thủng, sẽ dẫn đến tình trạng nhiễm khuẩn (do vi khuẩn trong ống tiêu hóa), làm nghẽn mạch (trong trường hợp xuất huyết). Cần phải mổ cấp cứu, làm sạch tại chỗ càng sớm càng tốt (trước 6 giờ).",
      "blocks": [
        {
          "type": "text",
          "text": "Khi chỉ định nhầm hoặc do quá trình chụp gây thủng, sẽ dẫn đến tình trạng nhiễm khuẩn (do vi khuẩn trong ống tiêu hóa), làm nghẽn mạch (trong trường hợp xuất huyết). Cần phải mổ cấp cứu, làm sạch tại chỗ càng sớm càng tốt (trước 6 giờ)."
        }
      ],
      "subsections": []
    },
    {
      "id": "cap-nhat-lan-cuoi",
      "title": "Cập nhật lần cuối",
      "content": "2017.",
      "blocks": [
        {
          "type": "text",
          "text": "2017."
        }
      ],
      "subsections": []
    }
  ],
  "tables": [],
  "quality": {
    "status": "pass",
    "issues": [],
    "has_update_section": true,
    "body_characters": 4475,
    "title_match": "pdf-bold-title-exact",
    "table_assets_verified": true
  }
}