{
  "schema_version": "10.1-source-paragraph-boundaries",
  "id": "simeticon",
  "title": "Simeticon",
  "aliases": [
    "simeticon"
  ],
  "source": {
    "book": "Dược thư Quốc gia Việt Nam",
    "edition": "Lần xuất bản thứ ba, 2023",
    "pdf_pages": {
      "start": 1479,
      "end": 1480
    },
    "printed_pages": {
      "start": 1485,
      "end": 1486
    },
    "extraction": {
      "start_title_pdf_page": 1479,
      "start_column": "right",
      "start_y": 591.5543823242188,
      "next_title_pdf_page": 1480,
      "next_column": "right",
      "next_y": 240.54095458984375,
      "boundary_method": "physical-source-title-band"
    }
  },
  "sections": [
    {
      "id": "thong-tin-au-chuyen-luan",
      "title": "Thông tin đầu chuyên luận",
      "content": "SIMETICON",
      "blocks": [
        {
          "type": "text",
          "text": "SIMETICON"
        }
      ],
      "subsections": []
    },
    {
      "id": "ten-chung-quoc-te",
      "title": "Tên chung quốc tế",
      "content": "Simeticone.\n\nMã ATC: A03AX13.\n\nLoại thuốc: Chống đầy hơi.",
      "blocks": [
        {
          "type": "text",
          "text": "Simeticone.\n\nMã ATC: A03AX13.\n\nLoại thuốc: Chống đầy hơi."
        }
      ],
      "subsections": []
    },
    {
      "id": "dang-thuoc-va-ham-luong",
      "title": "Dạng thuốc và hàm lượng",
      "content": "Viên nén: 40 mg; 80 mg, 125 mg.\n\nViên nén để nhai: 80 mg, 125 mg, 150 mg, 166 mg.\n\nNang mềm (chứa chất lỏng): 40 mg; 125 mg, 166 mg, 180 mg, 250 mg.\n\nDung dịch uống: 20 mg/0,3 ml; 600 mg/15 ml; 1 g/15 ml; 1 667 mg/25 ml; 4,5 g/15 ml.\n\nHỗn dịch uống: 40 mg/0,6 mg; 40 mg/ml (lọ 50 ml); 50 mg/5 ml.\n\nThuốc uống nhỏ giọt: 8,4 mg/ml (100 ml).",
      "blocks": [
        {
          "type": "text",
          "text": "Viên nén: 40 mg; 80 mg, 125 mg.\n\nViên nén để nhai: 80 mg, 125 mg, 150 mg, 166 mg.\n\nNang mềm (chứa chất lỏng): 40 mg; 125 mg, 166 mg, 180 mg, 250 mg.\n\nDung dịch uống: 20 mg/0,3 ml; 600 mg/15 ml; 1 g/15 ml; 1 667 mg/25 ml; 4,5 g/15 ml.\n\nHỗn dịch uống: 40 mg/0,6 mg; 40 mg/ml (lọ 50 ml); 50 mg/5 ml.\n\nThuốc uống nhỏ giọt: 8,4 mg/ml (100 ml)."
        }
      ],
      "subsections": []
    },
    {
      "id": "duoc-luc-hoc",
      "title": "Dược lực học",
      "content": "Simeticon là hỗn hợp polydimethylsiloxan và silicon dioxyd, có tác dụng chống tạo bọt. Simeticon làm giảm sức căng bề mặt của các bọt khí, làm vỡ hoặc kết tụ chúng lại và bị tống ra ngoài, nhờ đó có tác dụng chống đầy hơi. Vì vậy, simeticon có tác dụng làm giảm các triệu chứng liên quan đến có quá nhiều khí ở đường tiêu hóa gây ra ở cả người lớn và trẻ em, như khi nuốt phải nhiều khí vào dạ dày hoặc có một số chất khí được tạo ra ở ruột do sự giáng hóa của những thức ăn không được tiêu hóa bởi các vi khuẩn ruột.\n\nSimeticon còn được dùng ở dạng kết hợp với thuốc kháng acid, thuốc chống co thắt và enzym tiêu hóa.",
      "blocks": [
        {
          "type": "text",
          "text": "Simeticon là hỗn hợp polydimethylsiloxan và silicon dioxyd, có tác dụng chống tạo bọt. Simeticon làm giảm sức căng bề mặt của các bọt khí, làm vỡ hoặc kết tụ chúng lại và bị tống ra ngoài, nhờ đó có tác dụng chống đầy hơi. Vì vậy, simeticon có tác dụng làm giảm các triệu chứng liên quan đến có quá nhiều khí ở đường tiêu hóa gây ra ở cả người lớn và trẻ em, như khi nuốt phải nhiều khí vào dạ dày hoặc có một số chất khí được tạo ra ở ruột do sự giáng hóa của những thức ăn không được tiêu hóa bởi các vi khuẩn ruột.\n\nSimeticon còn được dùng ở dạng kết hợp với thuốc kháng acid, thuốc chống co thắt và enzym tiêu hóa."
        }
      ],
      "subsections": []
    },
    {
      "id": "duoc-ong-hoc",
      "title": "Dược động học",
      "content": "Simeticon có tính trơ về sinh lý. Sau khi uống, thuốc không hấp thu qua đường tiêu hóa, cũng không cản trở bài tiết acid dạ dày hoặc hấp thu các chất dinh dưỡng. Simeticon được thải trừ dưới dạng không biến đổi trong phân.",
      "blocks": [
        {
          "type": "text",
          "text": "Simeticon có tính trơ về sinh lý. Sau khi uống, thuốc không hấp thu qua đường tiêu hóa, cũng không cản trở bài tiết acid dạ dày hoặc hấp thu các chất dinh dưỡng. Simeticon được thải trừ dưới dạng không biến đổi trong phân."
        }
      ],
      "subsections": []
    },
    {
      "id": "chi-inh",
      "title": "Chỉ định",
      "content": "Giảm triệu chứng đầy hơi, trướng bụng và các triệu chứng khác liên quan đến quá nhiều khí ở đường tiêu hóa.\n\nSimeticon không còn được FDA cấp phép lưu hành ở Mỹ do liên quan đến độ an toàn và hiệu quả của thuốc.",
      "blocks": [
        {
          "type": "text",
          "text": "Giảm triệu chứng đầy hơi, trướng bụng và các triệu chứng khác liên quan đến quá nhiều khí ở đường tiêu hóa.\n\nSimeticon không còn được FDA cấp phép lưu hành ở Mỹ do liên quan đến độ an toàn và hiệu quả của thuốc."
        }
      ],
      "subsections": []
    },
    {
      "id": "chong-chi-inh",
      "title": "Chống chỉ định",
      "content": "Quá mẫn với simeticon.\n\nThủng hoặc tắc ruột (đã biết hoặc nghi ngờ).",
      "blocks": [
        {
          "type": "text",
          "text": "Quá mẫn với simeticon.\n\nThủng hoặc tắc ruột (đã biết hoặc nghi ngờ)."
        }
      ],
      "subsections": []
    },
    {
      "id": "than-trong",
      "title": "Thận trọng",
      "content": "Thận trọng khi dùng simeticon để điều trị cơn đau bụng ở trẻ nhỏ.\n\nKhông dùng quá liều khuyến cáo.\n\nTránh đồ uống có carbonat (soda hoặc nước ngọt) hoặc các thức ăn có thể làm tăng lượng khí trong dạ dày.",
      "blocks": [
        {
          "type": "text",
          "text": "Thận trọng khi dùng simeticon để điều trị cơn đau bụng ở trẻ nhỏ.\n\nKhông dùng quá liều khuyến cáo.\n\nTránh đồ uống có carbonat (soda hoặc nước ngọt) hoặc các thức ăn có thể làm tăng lượng khí trong dạ dày."
        }
      ],
      "subsections": []
    },
    {
      "id": "thoi-ky-mang-thai",
      "title": "Thời kỳ mang thai",
      "content": "Không rõ thuốc có qua được nhau thai hay không, nhưng do hấp thu của simeticon qua ruột bị hạn chế, điều đó làm giảm khả năng phơi nhiễm đối với thai nhi.",
      "blocks": [
        {
          "type": "text",
          "text": "Không rõ thuốc có qua được nhau thai hay không, nhưng do hấp thu của simeticon qua ruột bị hạn chế, điều đó làm giảm khả năng phơi nhiễm đối với thai nhi."
        }
      ],
      "subsections": []
    },
    {
      "id": "thoi-ky-cho-con-bu",
      "title": "Thời kỳ cho con bú",
      "content": "Không biết simeticon có được bài tiết vào sữa mẹ hay không, cũng không có báo cáo về dùng thuốc trong thời kỳ cho con bú. Cần cân nhắc nguy cơ/lợi ích khi sử dụng thuốc này cho bà mẹ đang cho con bú.",
      "blocks": [
        {
          "type": "text",
          "text": "Không biết simeticon có được bài tiết vào sữa mẹ hay không, cũng không có báo cáo về dùng thuốc trong thời kỳ cho con bú. Cần cân nhắc nguy cơ/lợi ích khi sử dụng thuốc này cho bà mẹ đang cho con bú."
        }
      ],
      "subsections": []
    },
    {
      "id": "tac-dung-khong-mong-muon-adr",
      "title": "Tác dụng không mong muốn (ADR)",
      "content": "Thường gặp Tiêu hóa: ỉa chảy (nhẹ), buồn nôn, nôn, ợ.\n\nHiếm gặp Táo bón, phản ứng quá mẫn như phát ban, viêm ngứa, phù mặt, phù lưỡi, khó thở.",
      "blocks": [
        {
          "type": "text",
          "text": "Thường gặp Tiêu hóa: ỉa chảy (nhẹ), buồn nôn, nôn, ợ.\n\nHiếm gặp Táo bón, phản ứng quá mẫn như phát ban, viêm ngứa, phù mặt, phù lưỡi, khó thở."
        }
      ],
      "subsections": []
    },
    {
      "id": "lieu-luong-va-cach-dung",
      "title": "Liều lượng và cách dùng",
      "content": "Cách dùng: Simeticon dùng đường uống. Dạng viên nhai phải nhai kỹ trước khi nuốt. Dạng nang mềm chứa dịch lỏng không được nhai. Lắc kỹ dung dịch thuốc uống trước khi dùng. Uống thuốc vào sau các bữa ăn và trước khi đi ngủ.\n\nLiều dùng Người lớn và trẻ em trên 12 tuổi: 40 - 125 mg/lần, 4 lần/ngày.\n\nDùng thuốc cần có sự theo dõi của thầy thuốc. Liều cao hơn liều bình thường cũng đã được dùng. Liều tối đa khi tự điều trị là 500 mg/ngày.\n\nTrẻ em 2 - 12 tuổi: 40 mg/lần, 4 lần/ngày. Liều tối đa khi tự điều trị là 240 mg/ngày.\n\nTrẻ em dưới 2 tuổi: 20 mg/lần, 4 lần/ngày. Liều tối đa khi tự điều trị là 120 mg/ngày.\n\nTrước khi nội soi dạ dày hoặc chụp X-quang ruột, người lớn dùng một liều 67 mg simeticon trong 2,5 ml nước, dưới dạng hỗn dịch uống, phụ với nước bơm làm sạch bóng khí trong quá trình nội soi tiêu hóa.",
      "blocks": [
        {
          "type": "text",
          "text": "Cách dùng: Simeticon dùng đường uống. Dạng viên nhai phải nhai kỹ trước khi nuốt. Dạng nang mềm chứa dịch lỏng không được nhai. Lắc kỹ dung dịch thuốc uống trước khi dùng. Uống thuốc vào sau các bữa ăn và trước khi đi ngủ.\n\nLiều dùng Người lớn và trẻ em trên 12 tuổi: 40 - 125 mg/lần, 4 lần/ngày.\n\nDùng thuốc cần có sự theo dõi của thầy thuốc. Liều cao hơn liều bình thường cũng đã được dùng. Liều tối đa khi tự điều trị là 500 mg/ngày.\n\nTrẻ em 2 - 12 tuổi: 40 mg/lần, 4 lần/ngày. Liều tối đa khi tự điều trị là 240 mg/ngày.\n\nTrẻ em dưới 2 tuổi: 20 mg/lần, 4 lần/ngày. Liều tối đa khi tự điều trị là 120 mg/ngày.\n\nTrước khi nội soi dạ dày hoặc chụp X-quang ruột, người lớn dùng một liều 67 mg simeticon trong 2,5 ml nước, dưới dạng hỗn dịch uống, phụ với nước bơm làm sạch bóng khí trong quá trình nội soi tiêu hóa."
        }
      ],
      "subsections": []
    },
    {
      "id": "tuong-tac-thuoc",
      "title": "Tương tác thuốc",
      "content": "Levothyroxin: Có thể làm giảm hấp thu levothyroxin, dẫn đến giảm hiệu quả của levothyroxin, gây giảm năng tuyến giáp. Nếu dùng đồng thời hai thuốc này phải uống cách nhau ít nhất 4 giờ.\n\nTheo dõi mức TSH và/hoặc các đánh giá khác về chức năng tuyến giáp khi bắt đầu dùng hoặc khi ngừng dùng simeticon khi điều trị levothyroxin.",
      "blocks": [
        {
          "type": "text",
          "text": "Levothyroxin: Có thể làm giảm hấp thu levothyroxin, dẫn đến giảm hiệu quả của levothyroxin, gây giảm năng tuyến giáp. Nếu dùng đồng thời hai thuốc này phải uống cách nhau ít nhất 4 giờ.\n\nTheo dõi mức TSH và/hoặc các đánh giá khác về chức năng tuyến giáp khi bắt đầu dùng hoặc khi ngừng dùng simeticon khi điều trị levothyroxin."
        }
      ],
      "subsections": []
    },
    {
      "id": "qua-lieu-va-xu-tri",
      "title": "Quá liều và xử trí",
      "content": "Không có ghi nhận trường hợp quá liều. Về lý thuyết, táo bón có thể xảy ra nếu quá liều. Điều trị bằng cách bổ sung chất lỏng và theo dõi bệnh nhân.",
      "blocks": [
        {
          "type": "text",
          "text": "Không có ghi nhận trường hợp quá liều. Về lý thuyết, táo bón có thể xảy ra nếu quá liều. Điều trị bằng cách bổ sung chất lỏng và theo dõi bệnh nhân."
        }
      ],
      "subsections": []
    },
    {
      "id": "cap-nhat-lan-cuoi",
      "title": "Cập nhật lần cuối",
      "content": "2018.",
      "blocks": [
        {
          "type": "text",
          "text": "2018."
        }
      ],
      "subsections": []
    }
  ],
  "tables": [],
  "quality": {
    "status": "source-layout-rebuilt-v10.1-source-paragraph-boundaries",
    "pdf_text_order": "left-column-then-right-column; visual line flow",
    "paragraph_policy": "Paragraph boundaries are source-derived and stored only as blank lines. The client preserves those boundaries exactly; it must not create a new paragraph from label words such as “Trẻ em:” or “Người lớn:”. A lower-case continuation fragment is merged only when it follows a non-terminal source fragment; table footnotes remain separate. No client-side anchor or length-based sentence splitter is allowed.",
    "table_policy": "source-table image inserted by PDF page/column/y position; table-cell text excluded from prose",
    "validation": {
      "raw_newline_inside_paragraph": false,
      "table_count": 0,
      "section_count": 15,
      "client_anchor_resegmentation_disabled": true,
      "client_length_sentence_chunking_disabled": true
    }
  }
}
