{
  "schema_version": "11.0.0-alpha.1",
  "id": "kem-oxyd",
  "title": "Kẽm Oxyd",
  "aliases": [
    "kem oxyd"
  ],
  "source": {
    "book": "Dược thư Quốc gia Việt Nam",
    "edition": "Lần xuất bản thứ ba, 2023",
    "pdf_pages": {
      "start": 957,
      "end": 957
    },
    "printed_pages": {
      "start": 963,
      "end": 963
    },
    "extraction": {
      "start_title_pdf_page": 957,
      "start_column": "left",
      "start_y": 183.39520263671875,
      "next_title_pdf_page": 957,
      "next_column": "right",
      "next_y": 345.3763122558594,
      "boundary_method": "physical-source-title-band"
    }
  },
  "parser": {
    "name": "medplus-duoc-thu-v11-structured-pdf-parser",
    "method": "PyMuPDF span -> line -> block",
    "content_source": "Duocthu2023.pdf",
    "old_json_usage": "id/title/page-boundary metadata and existing table asset path only; old content is not used",
    "column_order": "left column -> right column -> next page",
    "block_model": [
      "heading",
      "subheading",
      "paragraph",
      "list",
      "table",
      "figure",
      "note"
    ],
    "table_policy": "no OCR; preserve existing duoc-thu-assets/<id>/pXXXX-tXX.png image_path"
  },
  "blocks": [
    {
      "id": "b0001",
      "type": "heading",
      "level": 1,
      "text": "KẼM OXYD",
      "page": 957,
      "printed_page": 963,
      "column": 0,
      "bbox": [
        142.0,
        183.4,
        197.83,
        197.24
      ],
      "style": {
        "font_size": 10.0,
        "bold_ratio": 1.0,
        "italic_ratio": 0.0,
        "fonts": [
          "TimesNewRomanPS-BoldMT"
        ]
      },
      "spans": [
        {
          "text": "KẼM OXYD",
          "bbox": [
            142.0,
            183.4,
            197.83,
            197.24
          ],
          "font": "TimesNewRomanPS-BoldMT",
          "fontsize": 10.0,
          "flags": 20,
          "bold": true,
          "italic": false
        }
      ]
    },
    {
      "id": "b0002",
      "type": "paragraph",
      "text": "Tên chung quốc tế: Zinc oxide.",
      "page": 957,
      "printed_page": 963,
      "column": 0,
      "bbox": [
        43.94,
        204.33,
        166.92,
        217.48
      ],
      "source": {
        "line_count": 1
      },
      "spans": [
        {
          "text": "Tên chung quốc tế",
          "bbox": [
            43.94,
            204.33,
            118.63,
            217.48
          ],
          "font": "TimesNewRomanPS-BoldMT",
          "fontsize": 9.5,
          "flags": 20,
          "bold": true,
          "italic": false
        },
        {
          "text": ": Zinc oxide.",
          "bbox": [
            118.63,
            204.48,
            166.92,
            217.28
          ],
          "font": "TimesNewRomanPSMT",
          "fontsize": 9.5,
          "flags": 4,
          "bold": false,
          "italic": false
        }
      ]
    },
    {
      "id": "b0003",
      "type": "paragraph",
      "text": "Mã ATC: C05AX04.",
      "page": 957,
      "printed_page": 963,
      "column": 0,
      "bbox": [
        43.94,
        216.24,
        125.82,
        229.38
      ],
      "source": {
        "line_count": 1
      },
      "spans": [
        {
          "text": "Mã ATC: ",
          "bbox": [
            43.94,
            216.24,
            84.39,
            229.38
          ],
          "font": "TimesNewRomanPS-BoldMT",
          "fontsize": 9.5,
          "flags": 20,
          "bold": true,
          "italic": false
        },
        {
          "text": "C05AX04.",
          "bbox": [
            84.4,
            216.39,
            125.82,
            229.18
          ],
          "font": "TimesNewRomanPSMT",
          "fontsize": 9.5,
          "flags": 4,
          "bold": false,
          "italic": false
        }
      ]
    },
    {
      "id": "b0004",
      "type": "paragraph",
      "text": "Loại thuốc: Thuốc bảo vệ da.",
      "page": 957,
      "printed_page": 963,
      "column": 0,
      "bbox": [
        43.94,
        228.14,
        158.45,
        241.29
      ],
      "source": {
        "line_count": 1
      },
      "spans": [
        {
          "text": "Loại thuốc: ",
          "bbox": [
            43.94,
            228.14,
            93.02,
            241.29
          ],
          "font": "TimesNewRomanPS-BoldMT",
          "fontsize": 9.5,
          "flags": 20,
          "bold": true,
          "italic": false
        },
        {
          "text": "Thuốc bảo vệ da.",
          "bbox": [
            93.02,
            228.29,
            158.45,
            241.09
          ],
          "font": "TimesNewRomanPSMT",
          "fontsize": 9.5,
          "flags": 4,
          "bold": false,
          "italic": false
        }
      ]
    },
    {
      "id": "b0005",
      "type": "heading",
      "level": 2,
      "text": "Dạng thuốc và hàm lượng",
      "page": 957,
      "printed_page": 963,
      "column": 0,
      "bbox": [
        43.94,
        246.04,
        148.85,
        259.19
      ],
      "style": {
        "font_size": 9.5,
        "bold_ratio": 1.0,
        "italic_ratio": 0.0,
        "fonts": [
          "TimesNewRomanPS-BoldMT"
        ]
      },
      "spans": [
        {
          "text": "Dạng thuốc và hàm lượng",
          "bbox": [
            43.94,
            246.04,
            148.85,
            259.19
          ],
          "font": "TimesNewRomanPS-BoldMT",
          "fontsize": 9.5,
          "flags": 20,
          "bold": true,
          "italic": false
        }
      ]
    },
    {
      "id": "b0006",
      "type": "paragraph",
      "text": "Kẽm oxyd thường được dùng phối hợp với các hoạt chất khác trong các chế phẩm gồm nhiều thành phần, dưới các dạng:",
      "page": 957,
      "printed_page": 963,
      "column": 0,
      "bbox": [
        43.94,
        258.1,
        298.27,
        282.8
      ],
      "source": {
        "line_count": 2
      }
    },
    {
      "id": "b0007",
      "type": "paragraph",
      "text": "Thuốc xịt: 10%.",
      "page": 957,
      "printed_page": 963,
      "column": 0,
      "bbox": [
        43.94,
        281.91,
        105.42,
        294.7
      ],
      "source": {
        "line_count": 1
      },
      "spans": [
        {
          "text": "Thuốc xịt: 10%.",
          "bbox": [
            43.94,
            281.91,
            105.42,
            294.7
          ],
          "font": "TimesNewRomanPSMT",
          "fontsize": 9.5,
          "flags": 4,
          "bold": false,
          "italic": false
        }
      ]
    },
    {
      "id": "b0008",
      "type": "paragraph",
      "text": "Kem: 6%, 11,3%, 13%.",
      "page": 957,
      "printed_page": 963,
      "column": 0,
      "bbox": [
        43.94,
        293.81,
        133.56,
        306.61
      ],
      "source": {
        "line_count": 1
      },
      "spans": [
        {
          "text": "Kem: 6%, 11,3%, 13%.",
          "bbox": [
            43.94,
            293.81,
            133.56,
            306.61
          ],
          "font": "TimesNewRomanPSMT",
          "fontsize": 9.5,
          "flags": 4,
          "bold": false,
          "italic": false
        }
      ]
    },
    {
      "id": "b0009",
      "type": "paragraph",
      "text": "Thuốc mỡ: 3,8%; 9,38%; 10%; 16%, 20%; 40%.",
      "page": 957,
      "printed_page": 963,
      "column": 0,
      "bbox": [
        43.94,
        305.72,
        229.19,
        318.51
      ],
      "source": {
        "line_count": 1
      },
      "spans": [
        {
          "text": "Thuốc mỡ: 3,8%; 9,38%; 10%; 16%, 20%; 40%.",
          "bbox": [
            43.94,
            305.72,
            229.19,
            318.51
          ],
          "font": "TimesNewRomanPSMT",
          "fontsize": 9.5,
          "flags": 4,
          "bold": false,
          "italic": false
        }
      ]
    },
    {
      "id": "b0010",
      "type": "paragraph",
      "text": "Bột nhão: 16,5%; 20%; 40%; 12,8%.",
      "page": 957,
      "printed_page": 963,
      "column": 0,
      "bbox": [
        43.94,
        317.62,
        184.85,
        330.42
      ],
      "source": {
        "line_count": 1
      },
      "spans": [
        {
          "text": "Bột nhão: 16,5%; 20%; 40%; 12,8%.",
          "bbox": [
            43.94,
            317.62,
            184.85,
            330.42
          ],
          "font": "TimesNewRomanPSMT",
          "fontsize": 9.5,
          "flags": 4,
          "bold": false,
          "italic": false
        }
      ]
    },
    {
      "id": "b0011",
      "type": "paragraph",
      "text": "Bột dùng ngoài: 9,1%.",
      "page": 957,
      "printed_page": 963,
      "column": 0,
      "bbox": [
        43.94,
        329.52,
        129.7,
        342.32
      ],
      "source": {
        "line_count": 1
      },
      "spans": [
        {
          "text": "Bột dùng ngoài: 9,1%.",
          "bbox": [
            43.94,
            329.52,
            129.7,
            342.32
          ],
          "font": "TimesNewRomanPSMT",
          "fontsize": 9.5,
          "flags": 4,
          "bold": false,
          "italic": false
        }
      ]
    },
    {
      "id": "b0012",
      "type": "heading",
      "level": 2,
      "text": "Dược lực học",
      "page": 957,
      "printed_page": 963,
      "column": 0,
      "bbox": [
        43.94,
        347.28,
        97.54,
        360.42
      ],
      "style": {
        "font_size": 9.5,
        "bold_ratio": 1.0,
        "italic_ratio": 0.0,
        "fonts": [
          "TimesNewRomanPS-BoldMT"
        ]
      },
      "spans": [
        {
          "text": "Dược lực học",
          "bbox": [
            43.94,
            347.28,
            97.54,
            360.42
          ],
          "font": "TimesNewRomanPS-BoldMT",
          "fontsize": 9.5,
          "flags": 20,
          "bold": true,
          "italic": false
        }
      ]
    },
    {
      "id": "b0013",
      "type": "paragraph",
      "text": "Kẽm oxyd có tính chất làm săn da và sát khuẩn nhẹ và được dùng bôi tại chỗ để bảo vệ, làm dịu tổn thương chàm (eczema) và các chỗ trợt da nhẹ. Kẽm oxyd thường được dùng với hắc ín than đá hoặc ichthammol để điều trị chàm. Kẽm oxyd phản xạ tia cực tím nên còn được dùng trong các thuốc bôi chống nắng.",
      "page": 957,
      "printed_page": 963,
      "column": 0,
      "bbox": [
        43.94,
        359.33,
        298.27,
        419.75
      ],
      "source": {
        "line_count": 5
      }
    },
    {
      "id": "b0014",
      "type": "paragraph",
      "text": "Trong phần lớn các chế phẩm chứa kẽm oxyd còn có những chất khác như titan oxyd, bismuth oxyd, glycerol, bôm (nhựa thơm) Peru, ichthammol... đặc biệt các chất mỡ có tính chất bít kín nên có thể dễ gây bội nhiễm. Một vài chất còn có thể gây dị ứng. Kẽm oxyd cũng còn là nguyên liệu để làm một số loại xi măng nha khoa.",
      "page": 957,
      "printed_page": 963,
      "column": 0,
      "bbox": [
        43.94,
        418.85,
        298.27,
        479.27
      ],
      "source": {
        "line_count": 5
      }
    },
    {
      "id": "b0015",
      "type": "paragraph",
      "text": "Khi trộn với acid phosphoric, kẽm oxyd tạo thành một vật liệu cứng mà thành phần chủ yếu là kẽm phosphat; vật liệu này trộn với dầu Đinh hương hoặc eugenol dùng để hàn răng tạm thời.",
      "page": 957,
      "printed_page": 963,
      "column": 0,
      "bbox": [
        43.94,
        478.37,
        298.28,
        514.98
      ],
      "source": {
        "line_count": 3
      }
    },
    {
      "id": "b0016",
      "type": "heading",
      "level": 2,
      "text": "Chỉ định",
      "page": 957,
      "printed_page": 963,
      "column": 0,
      "bbox": [
        43.94,
        519.93,
        79.58,
        533.08
      ],
      "style": {
        "font_size": 9.5,
        "bold_ratio": 1.0,
        "italic_ratio": 0.0,
        "fonts": [
          "TimesNewRomanPS-BoldMT"
        ]
      },
      "spans": [
        {
          "text": "Chỉ định",
          "bbox": [
            43.94,
            519.93,
            79.58,
            533.08
          ],
          "font": "TimesNewRomanPS-BoldMT",
          "fontsize": 9.5,
          "flags": 20,
          "bold": true,
          "italic": false
        }
      ]
    },
    {
      "id": "b0017",
      "type": "paragraph",
      "text": "Dưới những dạng thuốc mỡ và hồ bôi dược dụng, kẽm oxyd được dùng rộng rãi trong điều trị da khô, các bệnh da và nhiễm khuẩn da như:",
      "page": 957,
      "printed_page": 963,
      "column": 0,
      "bbox": [
        43.94,
        531.99,
        298.27,
        568.6
      ],
      "source": {
        "line_count": 3
      }
    },
    {
      "id": "b0018",
      "type": "paragraph",
      "text": "Vùng da bị kích ứng do lỗ dò tiêu hóa, hậu môn nhân tạo, mở thông bàng quang.",
      "page": 957,
      "printed_page": 963,
      "column": 0,
      "bbox": [
        43.94,
        567.7,
        298.27,
        592.4
      ],
      "source": {
        "line_count": 2
      }
    },
    {
      "id": "b0019",
      "type": "paragraph",
      "text": "Điều trị hỗ trợ chàm (eczema).",
      "page": 957,
      "printed_page": 963,
      "column": 0,
      "bbox": [
        43.94,
        591.51,
        163.19,
        604.31
      ],
      "source": {
        "line_count": 1
      },
      "spans": [
        {
          "text": "Điều trị hỗ trợ chàm (eczema). ",
          "bbox": [
            43.94,
            591.51,
            163.19,
            604.31
          ],
          "font": "TimesNewRomanPSMT",
          "fontsize": 9.5,
          "flags": 4,
          "bold": false,
          "italic": false
        }
      ]
    },
    {
      "id": "b0020",
      "type": "paragraph",
      "text": "Vết bỏng nông, không rộng.",
      "page": 957,
      "printed_page": 963,
      "column": 0,
      "bbox": [
        43.94,
        603.42,
        151.07,
        616.21
      ],
      "source": {
        "line_count": 1
      },
      "spans": [
        {
          "text": "Vết bỏng nông, không rộng.",
          "bbox": [
            43.94,
            603.42,
            151.07,
            616.21
          ],
          "font": "TimesNewRomanPSMT",
          "fontsize": 9.5,
          "flags": 4,
          "bold": false,
          "italic": false
        }
      ]
    },
    {
      "id": "b0021",
      "type": "paragraph",
      "text": "Cháy nắng, hồng ban do bị chiếu nắng, bảo vệ da do nắng.",
      "page": 957,
      "printed_page": 963,
      "column": 0,
      "bbox": [
        43.94,
        615.32,
        266.36,
        628.12
      ],
      "source": {
        "line_count": 1
      },
      "spans": [
        {
          "text": "Cháy nắng, hồng ban do bị chiếu nắng, bảo vệ da do nắng.",
          "bbox": [
            43.94,
            615.32,
            266.36,
            628.12
          ],
          "font": "TimesNewRomanPSMT",
          "fontsize": 9.5,
          "flags": 4,
          "bold": false,
          "italic": false
        }
      ]
    },
    {
      "id": "b0022",
      "type": "paragraph",
      "text": "Trứng cá, côn trùng châm đốt, ban do tã lót, vảy da đầu, tăng tiết nhờn, chốc, nấm da, vảy nến, loét giãn tĩnh mạch, ngứa.",
      "page": 957,
      "printed_page": 963,
      "column": 0,
      "bbox": [
        43.94,
        627.22,
        298.27,
        651.92
      ],
      "source": {
        "line_count": 2
      }
    },
    {
      "id": "b0023",
      "type": "heading",
      "level": 2,
      "text": "Chống chỉ định",
      "page": 957,
      "printed_page": 963,
      "column": 0,
      "bbox": [
        43.94,
        656.88,
        106.24,
        670.03
      ],
      "style": {
        "font_size": 9.5,
        "bold_ratio": 1.0,
        "italic_ratio": 0.0,
        "fonts": [
          "TimesNewRomanPS-BoldMT"
        ]
      },
      "spans": [
        {
          "text": "Chống chỉ định",
          "bbox": [
            43.94,
            656.88,
            106.24,
            670.03
          ],
          "font": "TimesNewRomanPS-BoldMT",
          "fontsize": 9.5,
          "flags": 20,
          "bold": true,
          "italic": false
        }
      ]
    },
    {
      "id": "b0024",
      "type": "paragraph",
      "text": "Quá mẫn với thuốc.",
      "page": 957,
      "printed_page": 963,
      "column": 0,
      "bbox": [
        43.94,
        668.94,
        119.15,
        681.73
      ],
      "source": {
        "line_count": 1
      },
      "spans": [
        {
          "text": "Quá mẫn với thuốc.",
          "bbox": [
            43.94,
            668.94,
            119.15,
            681.73
          ],
          "font": "TimesNewRomanPSMT",
          "fontsize": 9.5,
          "flags": 4,
          "bold": false,
          "italic": false
        }
      ]
    },
    {
      "id": "b0025",
      "type": "paragraph",
      "text": "Tổn thương da bị nhiễm khuẩn.",
      "page": 957,
      "printed_page": 963,
      "column": 0,
      "bbox": [
        43.94,
        680.84,
        163.88,
        693.64
      ],
      "source": {
        "line_count": 1
      },
      "spans": [
        {
          "text": "Tổn thương da bị nhiễm khuẩn.",
          "bbox": [
            43.94,
            680.84,
            163.88,
            693.64
          ],
          "font": "TimesNewRomanPSMT",
          "fontsize": 9.5,
          "flags": 4,
          "bold": false,
          "italic": false
        }
      ]
    },
    {
      "id": "b0026",
      "type": "heading",
      "level": 2,
      "text": "Thận trọng",
      "page": 957,
      "printed_page": 963,
      "column": 0,
      "bbox": [
        43.94,
        698.59,
        90.13,
        711.74
      ],
      "style": {
        "font_size": 9.5,
        "bold_ratio": 1.0,
        "italic_ratio": 0.0,
        "fonts": [
          "TimesNewRomanPS-BoldMT"
        ]
      },
      "spans": [
        {
          "text": "Thận trọng",
          "bbox": [
            43.94,
            698.59,
            90.13,
            711.74
          ],
          "font": "TimesNewRomanPS-BoldMT",
          "fontsize": 9.5,
          "flags": 20,
          "bold": true,
          "italic": false
        }
      ],
      "note_role": "than trong",
      "v11_fix": "note_title_reclassified_as_heading_alpha5"
    },
    {
      "id": "b0027",
      "type": "paragraph",
      "text": "Trước khi bôi thuốc và trong quá trình điều trị phải đảm bảo vô khuẩn vùng được bôi thuốc vì có thể bội nhiễm ở các vùng bị thuốc che phủ.",
      "page": 957,
      "printed_page": 963,
      "column": 0,
      "bbox": [
        43.94,
        710.65,
        298.27,
        747.25
      ],
      "source": {
        "line_count": 3
      }
    },
    {
      "id": "b0028",
      "type": "paragraph",
      "text": "Một số chế phẩm không thích hợp với các tổn thương có tiết dịch.",
      "page": 957,
      "printed_page": 963,
      "column": 0,
      "bbox": [
        43.94,
        746.36,
        294.78,
        759.16
      ],
      "source": {
        "line_count": 1
      },
      "spans": [
        {
          "text": "Một số chế phẩm không thích hợp với các tổn thương có tiết dịch.",
          "bbox": [
            43.94,
            746.36,
            294.78,
            759.16
          ],
          "font": "TimesNewRomanPSMT",
          "fontsize": 9.5,
          "flags": 4,
          "bold": false,
          "italic": false
        }
      ]
    },
    {
      "id": "b0029",
      "type": "heading",
      "level": 2,
      "text": "Tác dụng không mong muốn (ADR)",
      "page": 957,
      "printed_page": 963,
      "column": 0,
      "bbox": [
        43.94,
        764.11,
        189.89,
        777.26
      ],
      "style": {
        "font_size": 9.5,
        "bold_ratio": 1.0,
        "italic_ratio": 0.0,
        "fonts": [
          "TimesNewRomanPS-BoldMT"
        ]
      },
      "spans": [
        {
          "text": "Tác dụng không mong muốn (ADR)",
          "bbox": [
            43.94,
            764.11,
            189.89,
            777.26
          ],
          "font": "TimesNewRomanPS-BoldMT",
          "fontsize": 9.5,
          "flags": 20,
          "bold": true,
          "italic": false
        }
      ]
    },
    {
      "id": "b0030",
      "type": "subheading",
      "level": 3,
      "text": "Hiếm gặp và rất hiếm gặp",
      "page": 957,
      "printed_page": 963,
      "column": 0,
      "bbox": [
        43.94,
        776.33,
        143.41,
        788.97
      ],
      "style": {
        "font_size": 9.5,
        "bold_ratio": 0.0,
        "italic_ratio": 1.0,
        "fonts": [
          "TimesNewRomanPS-ItalicMT"
        ]
      },
      "spans": [
        {
          "text": "Hiếm gặp và rất hiếm gặp",
          "bbox": [
            43.94,
            776.33,
            143.41,
            788.97
          ],
          "font": "TimesNewRomanPS-ItalicMT",
          "fontsize": 9.5,
          "flags": 6,
          "bold": false,
          "italic": true
        }
      ]
    },
    {
      "id": "b0031",
      "type": "paragraph",
      "text": "Các tá dược, bôm (nhựa thơm) Peru, lanolin có thể gây chàm tiếp xúc.",
      "page": 957,
      "printed_page": 963,
      "column": 0,
      "bbox": [
        43.94,
        788.07,
        295.93,
        800.87
      ],
      "source": {
        "line_count": 1
      },
      "spans": [
        {
          "text": "Các tá dược, bôm (nhựa thơm) Peru, lanolin có thể gây chàm tiếp xúc.",
          "bbox": [
            43.94,
            788.07,
            295.93,
            800.87
          ],
          "font": "TimesNewRomanPSMT",
          "fontsize": 9.5,
          "flags": 4,
          "bold": false,
          "italic": false
        }
      ]
    },
    {
      "id": "b0032",
      "type": "paragraph",
      "text": "Dị ứng với một trong các thành phần của chế phẩm.",
      "page": 957,
      "printed_page": 963,
      "column": 1,
      "bbox": [
        307.89,
        63.32,
        504.17,
        76.12
      ],
      "source": {
        "line_count": 1
      },
      "spans": [
        {
          "text": "Dị ứng với một trong các thành phần của chế phẩm.",
          "bbox": [
            307.89,
            63.32,
            504.17,
            76.12
          ],
          "font": "TimesNewRomanPSMT",
          "fontsize": 9.5,
          "flags": 4,
          "bold": false,
          "italic": false
        }
      ]
    },
    {
      "id": "b0033",
      "type": "heading",
      "level": 2,
      "text": "Hướng dẫn cách xử trí ADR",
      "page": 957,
      "printed_page": 963,
      "column": 1,
      "bbox": [
        307.89,
        81.13,
        422.45,
        94.28
      ],
      "style": {
        "font_size": 9.5,
        "bold_ratio": 1.0,
        "italic_ratio": 0.0,
        "fonts": [
          "TimesNewRomanPS-BoldMT"
        ]
      },
      "spans": [
        {
          "text": "Hướng dẫn cách xử trí ADR",
          "bbox": [
            307.89,
            81.13,
            422.45,
            94.28
          ],
          "font": "TimesNewRomanPS-BoldMT",
          "fontsize": 9.5,
          "flags": 20,
          "bold": true,
          "italic": false
        }
      ]
    },
    {
      "id": "b0034",
      "type": "paragraph",
      "text": "Ngừng dùng chế phẩm.",
      "page": 957,
      "printed_page": 963,
      "column": 1,
      "bbox": [
        307.89,
        93.24,
        396.94,
        106.04
      ],
      "source": {
        "line_count": 1
      },
      "spans": [
        {
          "text": "Ngừng dùng chế phẩm.",
          "bbox": [
            307.89,
            93.24,
            396.94,
            106.04
          ],
          "font": "TimesNewRomanPSMT",
          "fontsize": 9.5,
          "flags": 4,
          "bold": false,
          "italic": false
        }
      ]
    },
    {
      "id": "b0035",
      "type": "heading",
      "level": 2,
      "text": "Liều lượng và cách dùng",
      "page": 957,
      "printed_page": 963,
      "column": 1,
      "bbox": [
        307.89,
        111.05,
        408.07,
        124.2
      ],
      "style": {
        "font_size": 9.5,
        "bold_ratio": 1.0,
        "italic_ratio": 0.0,
        "fonts": [
          "TimesNewRomanPS-BoldMT"
        ]
      },
      "spans": [
        {
          "text": "Liều lượng và cách dùng",
          "bbox": [
            307.89,
            111.05,
            408.07,
            124.2
          ],
          "font": "TimesNewRomanPS-BoldMT",
          "fontsize": 9.5,
          "flags": 20,
          "bold": true,
          "italic": false
        }
      ]
    },
    {
      "id": "b0036",
      "type": "paragraph",
      "text": "Tổn thương trên da: Sau khi khử khuẩn, bôi đều một lớp thuốc mỏng lên vùng da bị tổn thương, 1 - 2 lần một ngày. Có thể dùng một miếng gạc vô khuẩn che lên.",
      "page": 957,
      "printed_page": 963,
      "column": 1,
      "bbox": [
        307.89,
        123.17,
        562.22,
        159.88
      ],
      "source": {
        "line_count": 3
      }
    },
    {
      "id": "b0037",
      "type": "paragraph",
      "text": "Chàm, nhất là chàm bị lichen hóa: Bôi một lớp dày chế phẩm (hồ nước) có chứa ichthammol, kẽm oxyd, glycerol lên vùng tổn thương, 2 - 3 lần một ngày.",
      "page": 957,
      "printed_page": 963,
      "column": 1,
      "bbox": [
        307.89,
        159.05,
        562.22,
        195.77
      ],
      "source": {
        "line_count": 3
      }
    },
    {
      "id": "b0038",
      "type": "paragraph",
      "text": "Đau ngứa hậu môn, nhất là trong những đợt trĩ: Bôi thuốc mỡ hoặc đặt đạn trực tràng có kẽm oxyd, bismuth oxyd, resorcin, sulphon, caraghenat vào hậu môn, ngày 2 - 3 lần, sau mỗi lần đi ngoài.",
      "page": 957,
      "printed_page": 963,
      "column": 1,
      "bbox": [
        307.89,
        194.93,
        562.22,
        231.65
      ],
      "source": {
        "line_count": 3
      }
    },
    {
      "id": "b0039",
      "type": "paragraph",
      "text": "Không nên dùng dài ngày. Nếu sau 7 - 10 ngày dùng không thấy đỡ thì phải thăm khám hậu môn trực tràng để tìm nguyên nhân gây chảy máu và cuối cùng phát hiện bệnh ác tính.",
      "page": 957,
      "printed_page": 963,
      "column": 1,
      "bbox": [
        307.89,
        230.82,
        562.22,
        267.53
      ],
      "source": {
        "line_count": 3
      }
    },
    {
      "id": "b0040",
      "type": "paragraph",
      "text": "Tổn thương do suy tĩnh mạch mạn tính, băng sau phẫu thuật giãn tĩnh mạch: Bôi phủ vết thương bằng chế phẩm có 20% kẽm oxyd trong vaselin.",
      "page": 957,
      "printed_page": 963,
      "column": 1,
      "bbox": [
        307.89,
        266.7,
        562.22,
        303.42
      ],
      "source": {
        "line_count": 3
      }
    },
    {
      "id": "b0041",
      "type": "heading",
      "text": "Cập nhật lần cuối",
      "page": 957,
      "printed_page": 963,
      "column": 1,
      "bbox": [
        307.89,
        308.74,
        410.41,
        321.38
      ],
      "source": {
        "line_count": 1
      },
      "spans": [
        {
          "text": "Cập nhật lần cuối: 2017. ",
          "bbox": [
            307.89,
            308.74,
            410.41,
            321.38
          ],
          "font": "TimesNewRomanPS-ItalicMT",
          "fontsize": 9.73,
          "flags": 6,
          "bold": false,
          "italic": true
        }
      ],
      "level": 2,
      "v11_fix": "cap_nhat_lan_cuoi_separate_toggle_alpha6"
    },
    {
      "id": "b0041",
      "type": "paragraph",
      "text": "2017.",
      "page": 957,
      "printed_page": 963,
      "column": 1,
      "bbox": [
        307.89,
        308.74,
        410.41,
        321.38
      ],
      "source": {
        "line_count": 1
      },
      "spans": [
        {
          "text": "Cập nhật lần cuối: 2017. ",
          "bbox": [
            307.89,
            308.74,
            410.41,
            321.38
          ],
          "font": "TimesNewRomanPS-ItalicMT",
          "fontsize": 9.73,
          "flags": 6,
          "bold": false,
          "italic": true
        }
      ],
      "v11_parent_heading": "Cập nhật lần cuối"
    }
  ],
  "sections": [
    {
      "id": "kem-oxyd",
      "title": "KẼM OXYD",
      "heading_block": "b0001",
      "blocks": [
        "b0002",
        "b0003",
        "b0004"
      ]
    },
    {
      "id": "dang-thuoc-va-ham-luong",
      "title": "Dạng thuốc và hàm lượng",
      "heading_block": "b0005",
      "blocks": [
        "b0006",
        "b0007",
        "b0008",
        "b0009",
        "b0010",
        "b0011"
      ]
    },
    {
      "id": "duoc-luc-hoc",
      "title": "Dược lực học",
      "heading_block": "b0012",
      "blocks": [
        "b0013",
        "b0014",
        "b0015"
      ]
    },
    {
      "id": "chi-inh",
      "title": "Chỉ định",
      "heading_block": "b0016",
      "blocks": [
        "b0017",
        "b0018",
        "b0019",
        "b0020",
        "b0021",
        "b0022"
      ]
    },
    {
      "id": "chong-chi-inh",
      "title": "Chống chỉ định",
      "heading_block": "b0023",
      "blocks": [
        "b0024",
        "b0025",
        "b0026",
        "b0027",
        "b0028"
      ]
    },
    {
      "id": "tac-dung-khong-mong-muon-adr",
      "title": "Tác dụng không mong muốn (ADR)",
      "heading_block": "b0029",
      "blocks": [
        "b0030",
        "b0031",
        "b0032"
      ]
    },
    {
      "id": "huong-dan-cach-xu-tri-adr",
      "title": "Hướng dẫn cách xử trí ADR",
      "heading_block": "b0033",
      "blocks": [
        "b0034"
      ]
    },
    {
      "id": "lieu-luong-va-cach-dung",
      "title": "Liều lượng và cách dùng",
      "heading_block": "b0035",
      "blocks": [
        "b0036",
        "b0037",
        "b0038",
        "b0039",
        "b0040",
        "b0041"
      ]
    }
  ],
  "quality": {
    "block_count": 41,
    "heading_count": 8,
    "subheading_count": 1,
    "paragraph_count": 31,
    "list_count": 0,
    "table_count": 0,
    "figure_count": 0,
    "note_count": 1,
    "page_count": 1
  }
}